odoo/addons/odoo_test_xmlrunner/README.rst
odoo/addons/odoo_test_xmlrunner/__init__.py
odoo/addons/odoo_test_xmlrunner/__manifest__.py
odoo/addons/odoo_test_xmlrunner/requirements.txt
odoo/addons/odoo_test_xmlrunner/i18n/it.po
odoo/addons/odoo_test_xmlrunner/i18n/odoo_test_xmlrunner.pot
odoo/addons/odoo_test_xmlrunner/odoo_tests/__init__.py
odoo/addons/odoo_test_xmlrunner/odoo_tests/loader.py
odoo/addons/odoo_test_xmlrunner/readme/CONFIGURATION.md
odoo/addons/odoo_test_xmlrunner/readme/CREDITS.md
odoo/addons/odoo_test_xmlrunner/readme/DESCRIPTION.md
odoo/addons/odoo_test_xmlrunner/readme/INSTALL.md
odoo/addons/odoo_test_xmlrunner/readme/USAGE.md
odoo/addons/odoo_test_xmlrunner/static/description/icon.png
odoo/addons/odoo_test_xmlrunner/static/description/index.html
odoo_addon_odoo_test_xmlrunner-16.0.1.0.1.1.dist-info/METADATA
odoo_addon_odoo_test_xmlrunner-16.0.1.0.1.1.dist-info/WHEEL
odoo_addon_odoo_test_xmlrunner-16.0.1.0.1.1.dist-info/top_level.txt
odoo_addon_odoo_test_xmlrunner-16.0.1.0.1.1.dist-info/RECORD
