Metadata-Version: 2.1
Name: odoo-addon-odoo_test_xmlrunner
Version: 16.0.1.0.1.1
Requires-Python: >=3.10
Requires-Dist: odoo>=16.0a,<16.1dev
Requires-Dist: unittest-xml-reporting
Summary: This module override Odoo testing method to run them with xmlrunner tool.
Home-page: https://github.com/OCA/server-tools
License: AGPL-3
Author: Smile, Odoo Community Association (OCA)
Author-email: support@odoo-community.org
Classifier: Programming Language :: Python
Classifier: Framework :: Odoo
Classifier: Framework :: Odoo :: 16.0
Classifier: License :: OSI Approved :: GNU Affero General Public License v3
